git_branch_list/__init__.py
git_branch_list/cli.py
git_branch_list/fzf_ui.py
git_branch_list/git_ops.py
git_branch_list/github.py
git_branch_list/progress.py
git_branch_list/render.py
git_branches-0.1.1.dist-info/licenses/LICENSE
git_branches-0.1.1.dist-info/METADATA
git_branches-0.1.1.dist-info/WHEEL
git_branches-0.1.1.dist-info/entry_points.txt
git_branches-0.1.1.dist-info/top_level.txt
git_branches-0.1.1.dist-info/RECORD
