Metadata-Version: 2.4
Name: git-branches
Version: 0.1.1
Summary: Interactive Git branch browser with fzf integration and GitHub PR status
Author-email: Your Name <your.email@example.com>
License-Expression: Apache-2.0
Keywords: git,fzf,github,cli,branch-management
Classifier: Development Status :: 4 - Beta
Classifier: Environment :: Console
Classifier: Intended Audience :: Developers
Classifier: Operating System :: OS Independent
Classifier: Programming Language :: Python :: 3
Classifier: Programming Language :: Python :: 3.12
Classifier: Topic :: Software Development :: Version Control :: Git
Classifier: Topic :: Utilities
Requires-Python: >=3.12
License-File: LICENSE
Requires-Dist: requests>=2.32.4
Provides-Extra: test
Requires-Dist: pytest>=8.0.0; extra == "test"
Requires-Dist: pytest-cov>=4.0.0; extra == "test"
Provides-Extra: dev
Requires-Dist: pytest>=8.0.0; extra == "dev"
Requires-Dist: ruff>=0.4.0; extra == "dev"
Requires-Dist: build>=1.0.0; extra == "dev"
Requires-Dist: pytest-cov>=4.0.0; extra == "dev"
Dynamic: license-file
